kuroco_api/CONFIG.py
kuroco_api/__init__.py
kuroco_api/kuroco_access.py
kuroco_api/kuroco_api.py
kuroco_api/kuroco_content.py
kuroco_api/kuroco_response.py
kuroco_api/kuroco_url.py
kuroco_embedding/CONFIG.py
kuroco_embedding/__init__.py
kuroco_embedding/kuroco_embedding.py
kuroco_embedding/kuroco_retriever.py
kuroco_embedding/tools.py
kuroco_py-0.0.3.1.dist-info/METADATA
kuroco_py-0.0.3.1.dist-info/WHEEL
kuroco_py-0.0.3.1.dist-info/RECORD
