Metadata-Version: 2.1
Name: kuroco-py
Version: 0.0.3.1
Summary: A Python client for Kuroco Headless CMS
License: Apache-2.0
Keywords: kuroco,headless,cms,api,client,langchain
Requires-Python: >=3.8.1,<4.0
Classifier: License :: OSI Approved :: Apache Software License
Classifier: Programming Language :: Python :: 3
Classifier: Programming Language :: Python :: 3.9
Classifier: Programming Language :: Python :: 3.10
Classifier: Programming Language :: Python :: 3.11
Requires-Dist: asyncclick (>=8.0.1.2)
Requires-Dist: langchain (>=0.0.300)
Requires-Dist: pandas (>=1.1.1)
